ai/backend/storage/VERSION
ai/backend/storage/__init__.py
ai/backend/storage/context.py
ai/backend/storage/context_types.py
ai/backend/storage/exception.py
ai/backend/storage/migration.py
ai/backend/storage/plugin.py
ai/backend/storage/py.typed
ai/backend/storage/server.py
ai/backend/storage/subproc.py
ai/backend/storage/types.py
ai/backend/storage/utils.py
ai/backend/storage/watcher.py
ai/backend/storage/api/__init__.py
ai/backend/storage/api/client.py
ai/backend/storage/api/manager.py
ai/backend/storage/api/types.py
ai/backend/storage/api/v1/__init__.py
ai/backend/storage/api/v1/registries/__init__.py
ai/backend/storage/api/v1/registries/huggingface.py
ai/backend/storage/api/v1/registries/reservoir.py
ai/backend/storage/api/v1/storages/__init__.py
ai/backend/storage/api/v1/storages/object_storage.py
ai/backend/storage/api/v1/storages/vfs_storage.py
ai/backend/storage/api/vfolder/__init__.py
ai/backend/storage/api/vfolder/handler.py
ai/backend/storage/bgtask/__init__.py
ai/backend/storage/bgtask/registry.py
ai/backend/storage/bgtask/tags.py
ai/backend/storage/bgtask/types.py
ai/backend/storage/bgtask/tasks/__init__.py
ai/backend/storage/bgtask/tasks/clone.py
ai/backend/storage/bgtask/tasks/delete.py
ai/backend/storage/bgtask/tasks/delete_files.py
ai/backend/storage/cli/__init__.py
ai/backend/storage/cli/__main__.py
ai/backend/storage/cli/config.py
ai/backend/storage/cli/context.py
ai/backend/storage/cli/dependencies.py
ai/backend/storage/cli/health.py
ai/backend/storage/cli/start_server.py
ai/backend/storage/client/__init__.py
ai/backend/storage/client/huggingface.py
ai/backend/storage/client/manager.py
ai/backend/storage/client/s3.py
ai/backend/storage/config/__init__.py
ai/backend/storage/config/loaders.py
ai/backend/storage/config/unified.py
ai/backend/storage/data/__init__.py
ai/backend/storage/data/storage/__init__.py
ai/backend/storage/data/storage/types.py
ai/backend/storage/dependencies/__init__.py
ai/backend/storage/dependencies/composer.py
backend_ai_storage_proxy-26.1.0.dist-info/METADATA
backend_ai_storage_proxy-26.1.0.dist-info/WHEEL
backend_ai_storage_proxy-26.1.0.dist-info/entry_points.txt
backend_ai_storage_proxy-26.1.0.dist-info/namespace_packages.txt
backend_ai_storage_proxy-26.1.0.dist-info/top_level.txt
backend_ai_storage_proxy-26.1.0.dist-info/RECORD
